django_dea/dea/__init__.py
django_dea/dea/admin.py
django_dea/dea/apps.py
django_dea/dea/managers.py
django_dea/dea/migrations/0001_initial.py
django_dea/dea/migrations/0002_intial_data.py
django_dea/dea/migrations/0003_view.py
django_dea/dea/migrations/__init__.py
django_dea/dea/models.py
django_dea/dea/tests.py
django_dea/dea/utils/__init__.py
django_dea/dea/utils/currency.py
django_dea/dea/utils/defaults.py
django_dea/dea/utils/exceptions.py
django_dea/dea/utils/new_currency.py
django_dea/dea/views.py
django_dea/django_dea/__init__.py
django_dea/django_dea/asgi.py
django_dea/django_dea/settings.py
django_dea/django_dea/urls.py
django_dea/django_dea/wsgi.py
django_dea/manage.py
django_dea-0.1.0.dist-info/METADATA
django_dea-0.1.0.dist-info/WHEEL
django_dea-0.1.0.dist-info/RECORD
